{
  "title": "Heart of Worship",
  "artist": "Matt Redman",
  "slides": [
    {
      "id": "a3b4c5d6-e7f8-9012-abcd-ef3456789023",
      "text": "When the music fades\nAll is stripped away\nAnd I simply come\nLonging just to bring\nSomething that's of worth\nThat will bless Your heart",
      "label": "Verse 1"
    },
    {
      "id": "a3b4c5d6-e7f8-9012-abcd-ef3456789024",
      "text": "I'll bring You more than a song\nFor a song in itself is not what You have required\nYou search much deeper within\nThrough the way things appear\nYou're looking into my heart",
      "label": "Chorus"
    },
    {
      "id": "a3b4c5d6-e7f8-9012-abcd-ef3456789025",
      "text": "I'm coming back to the heart of worship\nAnd it's all about You, it's all about You, Jesus\nI'm sorry Lord for the thing I've made it\nWhen it's all about You, it's all about You, Jesus",
      "label": "Chorus 2"
    },
    {
      "id": "a3b4c5d6-e7f8-9012-abcd-ef3456789026",
      "text": "King of endless worth\nNo one could express\nHow much You deserve\nThough I'm weak and poor\nAll I have is Yours\nEvery single breath",
      "label": "Verse 2"
    }
  ],
  "id": "b3c4d5e6-f7a8-9012-bcde-f34567890134"
}
