{
  "title": "I dire Gägewart",
  "artist": "Neui Dimensione ICF Bern",
  "slides": [
    {
      "id": "a7b8c9d0-e1f2-3456-abcd-ef7890123467",
      "text": "I gseh so viu Liebi wo verhäbt\nI gspüre so viu Wermi womi umgit\nI Rueh mim Härz wo mir zeigt, dass du mir läbsch\nEs Vertroue, e feschte Gloube, dass du mi nie wirsch verlah",
      "label": "Verse 1"
    },
    {
      "id": "a7b8c9d0-e1f2-3456-abcd-ef7890123468",
      "text": "Es isch e Sehnsucht da nach meh vo dir\nE töife Wunsch mim Härz\nEs Gfüehl wo mir seit, i cha nid ohni di si\nZ'Verlange zieht mi nöcher zu dir, dini Gägewart\nFür immer und ewig woti bi dir si",
      "label": "Pre-Chorus"
    },
    {
      "id": "a7b8c9d0-e1f2-3456-abcd-ef7890123469",
      "text": "Drum strecki mini Händ zu dir hi\nMöcht ganz nöch bi dir si\nI dire Gägewart woti blibe Herr\nMini Seeu u mis Härz schreie nach dir",
      "label": "Chorus"
    },
    {
      "id": "a7b8c9d0-e1f2-3456-abcd-ef7890123470",
      "text": "Vouer Ehrfurcht stahni da\nS'git nüt wo näbe dir cha bestah\nWas für ne Gott, für ne Chraft une Heiligkeit\nChani erläbe, darfi erfasse u mi völlig druf verlah",
      "label": "Verse 2"
    }
  ],
  "id": "b7c8d9e0-f1a2-3456-bcde-f78901234578"
}
