{
  "title": "This love",
  "artist": "",
  "slides": [
    {
      "id": "c1d2e3f4-a5b6-7890-cdef-123456789045",
      "text": "This love, this amazing love\nThis love, this unconditional love\nThis love, this sacrificial love\nHas saved me",
      "label": "Chorus"
    },
    {
      "id": "c1d2e3f4-a5b6-7890-cdef-123456789046",
      "text": "You gave Your life for me\nYou died upon the cross\nYou rose again for me\nThis is love",
      "label": "Verse"
    }
  ],
  "id": "d1e2f3a4-b5c6-7890-def1-234567890156"
}
